CherrySQL/__init__.py
CherrySQL/SQL3/Tables3.xlsx
CherrySQL/SQL3/VAR3.sql
CherrySQL/SQL3/config.py
CherrySQL/SQL3/database.py
CherrySQL/SQL3/icon.ico
CherrySQL/SQL3/logo.png
CherrySQL/SQL3/main.py
CherrySQL/SQL4/Tables4.xlsx
CherrySQL/SQL4/VAR4.sql
CherrySQL/SQL4/config.py
CherrySQL/SQL4/database.py
CherrySQL/SQL4/icon.ico
CherrySQL/SQL4/logo.png
CherrySQL/SQL4/main.py
CherrySQL/SQL5/Tables5.xlsx
CherrySQL/SQL5/VAR5.sql
CherrySQL/SQL5/config.py
CherrySQL/SQL5/database.py
CherrySQL/SQL5/icon.ico
CherrySQL/SQL5/logo.png
CherrySQL/SQL5/main.py
cherry_sql-0.2.0.dist-info/METADATA
cherry_sql-0.2.0.dist-info/WHEEL
cherry_sql-0.2.0.dist-info/top_level.txt
cherry_sql-0.2.0.dist-info/RECORD
