Metadata-Version: 2.1
Name: cherry-sql
Version: 0.2.0
Summary: Библиотека для работы с SQL и вспомогательными файлами
Home-page: https://pypi.org/project/cherry-sql/
Author: shareofpie
Author-email: your@email.com
Classifier: Programming Language :: Python :: 3
Classifier: License :: OSI Approved :: MIT License
Classifier: Operating System :: OS Independent
Requires-Python: >=3.7
